open_dread_rando_exlaunch/__init__.py
open_dread_rando_exlaunch/py.typed
open_dread_rando_exlaunch/version.py
open_dread_rando_exlaunch/__pyinstaller/__init__.py
open_dread_rando_exlaunch/__pyinstaller/hook-open_dread_rando_exlaunch.py
open_dread_rando_exlaunch/deploy/main.npdm
open_dread_rando_exlaunch/deploy/subsdk9
open_dread_rando_exlaunch-1.1.0.dist-info/LICENSE
open_dread_rando_exlaunch-1.1.0.dist-info/METADATA
open_dread_rando_exlaunch-1.1.0.dist-info/WHEEL
open_dread_rando_exlaunch-1.1.0.dist-info/entry_points.txt
open_dread_rando_exlaunch-1.1.0.dist-info/top_level.txt
open_dread_rando_exlaunch-1.1.0.dist-info/RECORD
