Metadata-Version: 2.2
Name: open-dread-rando-exlaunch
Version: 1.1.0
Summary: Exlaunch binary files for open-dread-rando.
Project-URL: Homepage, https://github.com/randovania/open-dread-rando-exlaunch
Classifier: License :: OSI Approved :: GNU General Public License v2 (GPLv2)
Classifier: Intended Audience :: Developers
Classifier: Programming Language :: Python :: 3.10
Classifier: Programming Language :: Python :: 3.11
Classifier: Programming Language :: Python :: 3.12
Classifier: Programming Language :: Python :: 3.13
Requires-Python: >=3.10
License-File: LICENSE
